Workbook

Sheet Raw Data
A1: Date of Date | B1: Department Name | C1: T1 | D1: Reporting Manager | E1: Employee ID | F1: Employee Name | G1: Client Name | H1: Project Name | I1: Job Name | J1: Work Item | K1: Description | L1: -No Value- | M1: Billable | N1: Non-Billable | O1: Total Hours | P1: Leave Hours | Q1: Non billable other than leave
A2: 46139 | B2: Administration | C2: 1275 - Devendra Singh - Rana | D2: Devendra Singh Nandan Singh Rana | E2: 1312 | F2: Kamda Brijeshkumar Rai | G2: SPRLINE CONSULTANCY PRIVATE LIMITED | H2: Admin Work | I2: Admin work | J2: Routine tasks | K2: Calendar Blocking Meeting Scheduling Internal Meeting Scheduling E-mail Communication | M2: 0 | N2: 4 | O2: 4 | P2: 0 | Q2: 4
A3: 46139 | B3: Administration | C3: 1275 - Devendra Singh - Rana | D3: Devendra Singh Nandan Singh Rana | E3: 1312 | F3: Kamda Brijeshkumar Rai | G3: SPRLINE CONSULTANCY PRIVATE LIMITED | H3: Admin Work | I3: Admin work | J3: Routine tasks | K3: Data Entry Invoice Documentation Client Greeting And office Visit Scanning Documents EL Entries EL Reminder sent to Client And their Entries and Documentation | M3: 0 | N3: 3 | O3: 3 | P3: 0 | Q3: 3
A4: 46139 | B4: Administration | C4: 1275 - Devendra Singh - Rana | D4: Devendra Singh Nandan Singh Rana | E4: 1312 | F4: Kamda Brijeshkumar Rai | G4: SPRLINE CONSULTANCY PRIVATE LIMITED | H4: Admin Work | I4: Admin work | J4: Routine tasks | K4: Internal Meeting | M4: 0 | N4: 1 | O4: 1 | P4: 0 | Q4: 1
A5: 46139 | B5: Administration | C5: 1279 - Vimal - Vadhiya | D5: Vimal Amrutlal Vadhiya | E5: 1275 | F5: Devendra Singh Nandan Singh Rana | G5: SPRLINE CONSULTANCY PRIVATE LIMITED | H5: Admin Work | I5: Admin work | J5: Repairs and Maintenance | K5: Cafeteria cupboard door and ceiling repairing work | M5: 0 | N5: 1.5 | O5: 1.5 | P5: 0 | Q5: 1.5
A6: 46139 | B6: Administration | C6: 1279 - Vimal - Vadhiya | D6: Vimal Amrutlal Vadhiya | E6: 1275 | F6: Devendra Singh Nandan Singh Rana | G6: SPRLINE CONSULTANCY PRIVATE LIMITED | H6: Admin Work | I6: Admin work | J6: Review | K6: HK and stationery stock check | M6: 0 | N6: 1 | O6: 1 | P6: 0 | Q6: 1
A7: 46139 | B7: Administration | C7: 1279 - Vimal - Vadhiya | D7: Vimal Amrutlal Vadhiya | E7: 1275 | F7: Devendra Singh Nandan Singh Rana | G7: SPRLINE CONSULTANCY PRIVATE LIMITED | H7: Admin Work | I7: Admin work | J7: Routine tasks | K7: Routine administrative coordination and daily operations management, floor visit, Cafeteria inspection visits during break timings (2 rounds), Team meeting | M7: 0 | N7: 5 | O7: 5 | P7: 0 | Q7: 5
A8: 46139 | B8: Administration | C8: 1279 - Vimal - Vadhiya | D8: Vimal Amrutlal Vadhiya | E8: 1275 | F8: Devendra Singh Nandan Singh Rana | G8: SPRLINE CONSULTANCY PRIVATE LIMITED | H8: Admin Work | I8: Events | J8: Company event | K8: Esparanza related meeting with HR team, quotation follow-ups with vendors | M8: 0 | N8: 1.5 | O8: 1.5 | P8: 0 | Q8: 1.5
A9: 46139 | B9: Administration | C9: 1279 - Vimal - Vadhiya | D9: Vimal Amrutlal Vadhiya | E9: 1275 | F9: Devendra Singh Nandan Singh Rana | G9: SPRLINE CONSULTANCY PRIVATE LIMITED | H9: Admin Work | I9: Meetings | J9: Meetings | K9: Meeting with Vimal Bhai | M9: 0 | N9: 0.2 | O9: 0.2 | P9: 0 | Q9: 0.2
A10: 46139 | B10: Business Development | C10: 1279 - Vimal - Vadhiya | D10: Thakkarar Surav Rajesh | E10: 1276 | F10: Thakkar Dhara Chandrakantbhai | G10: SPRLINE CONSULTANCY PRIVATE LIMITED | H10: Marketing & BD | I10: Business Development tasks | J10: Corporate Growth and Scale | K10: Hubspot BDO Sequence email | M10: 0 | N10: 1 | O10: 1 | P10: 0 | Q10: 1
A11: 46139 | B11: Business Development | C11: 1279 - Vimal - Vadhiya | D11: Thakkarar Surav Rajesh | E11: 1276 | F11: Thakkar Dhara Chandrakantbhai | G11: SPRLINE CONSULTANCY PRIVATE LIMITED | H11: Marketing & BD | I11: Business Development tasks | J11: Corporate Growth and Scale | K11: Review all pin website | M11: 0 | N11: 0.5 | O11: 0.5 | P11: 0 | Q11: 0.5
A12: 46139 | B12: Business Development | C12: 1279 - Vimal - Vadhiya | D12: Thakkarar Surav Rajesh | E12: 1276 | F12: Thakkar Dhara Chandrakantbhai | G12: SPRLINE CONSULTANCY PRIVATE LIMITED | H12: Marketing & BD | I12: Business Development tasks | J12: Corporate Growth and Scale | K12: SA email follow-up | M12: 0 | N12: 0.8333333 | O12: 0.8333333 | P12: 0 | Q12: 0.8333333
A13: 46139 | B13: Business Development | C13: 1279 - Vimal - Vadhiya | D13: Thakkarar Surav Rajesh | E13: 1276 | F13: Thakkar Dhara Chandrakantbhai | G13: SPRLINE CONSULTANCY PRIVATE LIMITED | H13: Marketing & BD | I13: Business Development tasks | J13: Corporate Growth and Scale | K13: Twitter / Reddit | M13: 0 | N13: 3 | O13: 3 | P13: 0 | Q13: 3
... A3526: 46144 | B3526: US Accounts | C3526: 1158 - Parshwa - Vora | D3526: Shaikh Firoz Rehman | E3526: 1178 | F3526: Soni Jehal | G3526: United States Gold Bureau | H3526: United States Gold Bureau | I3526: ACC-Bookkeeping Management | J3526: Review/Reconciliation/Reporting | K3526: USGB-Bank reconciliation - Texas bank reports download & Indentify the transactions USGB-Merge the reports and identify the way to make the process easy | M3526: 4.5 | N3526: 0 | O3526: 4.5 | P3526: 0 | Q3526: 0
M3527: 0 | N3527: 0 | P3527: 0 | Q3527: 0
M3528: 0 | N3528: 0 | P3528: 0 | Q3528: 0
M3529: 0 | N3529: 0 | P3529: 0 | Q3529: 0
M3530: 0 | N3530: 0 | P3530: 0 | Q3530: 0
M3531: 0 | N3531: 0 | P3531: 0 | Q3531: 0
M3532: 0 | N3532: 0 | P3532: 0 | Q3532: 0
M3533: 0 | N3533: 0 | P3533: 0 | Q3533: 0
M3534: 0 | N3534: 0 | P3534: 0 | Q3534: 0
M3535: 0 | N3535: 0 | P3535: 0 | Q3535: 0
M3536: 0 | N3536: 0 | P3536: 0 | Q3536: 0
M3537: 0 | N3537: 0 | P3537: 0 | Q3537: 0
M3538: 0 | N3538: 0 | P3538: 0 | Q3538: 0
... M10914: 0 | N10914: 0 | P10914: 0 | Q10914: 0

Sheet Expected hours per employee
A1: Sr no | B1: Employee ID | C1: Department Name | D1: Employee Name | E1: Expected Hours | F1: FTE assigned/unassigned
A2: 1 | B2: 1275 | C2: Administration | D2: Devendra Singh Nandan Singh Rana | E2: 45 | F2: Assigned
A3: 2 | B3: 1312 | C3: Administration | D3: Kamda Brijeshkumar Rai | E3: 45 | F3: Assigned
A4: 4 | B4: 1276 | C4: Business Development | D4: Thakkar Dhara Chandrakantbhai | E4: 40 | F4: Assigned
A5: 5 | B5: 1118 | C5: Business Development | D5: Thakkarar Surav Rajesh | E5: 40 | F5: Assigned
A6: 6 | B6: 1371 | C6: Finance | D6: Doshi Ankit Yogeshchandra | E6: 46 | F6: Assigned
A7: 7 | B7: 1249 | C7: Finance | D7: Kapil Kanaiyalal Popat | E7: 46 | F7: Assigned
A8: 8 | B8: 229 | C8: Finance | D8: Krunal K Panchal | E8: 46 | F8: Assigned
A9: 10 | B9: 1379 | C9: HR | D9: Bhadiyadra Bansari Ashokkumar | E9: 40 | F9: Assigned
A10: 11 | B10: 1366 | C10: HR | D10: Digvijaysinh Indrajitsinh Rathod | E10: 40 | F10: Assigned
A11: 12 | B11: 1234 | C11: HR | D11: Kavya Punitbhai Trivedi | E11: 40 | F11: Assigned
A12: 13 | B12: 1245 | C12: HR | D12: Khattri Aakash Premkumar | E12: 40 | F12: Assigned
A13: 14 | B13: 1342 | C13: HR | D13: Musini Nitish Shankar | E13: 40 | F13: Assigned
... A27: 28 | B27: 1283 | C27: Marketing | D27: Snehal Vinodkumar Sharma | E27: 40 | F27: Assigned
A28: 29 | B28: 153 | C28: UK Accounts and Tax | D28: Khalas Nikunjbhai | E28: =35+7 | F28: Assigned
A29: 30 | B29: 1331 | C29: US Accounts | D29: Adarsh Mukeshbhai Contractor | E29: 40 | F29: Assigned
A30: 31 | B30: 1328 | C30: US Accounts | D30: Akil I Mansuri | E30: 40 | F30: Assigned
A31: 32 | B31: 1318 | C31: US Accounts | D31: Anantkumar Prahladbhai Suthar | E31: 40 | F31: Assigned
A32: 33 | B32: 1166 | C32: US Accounts | D32: Bachani Aniket | E32: 40 | F32: Assigned
A33: 34 | B33: 1310 | C33: US Accounts | D33: Bagaria Umang | E33: 40 | F33: Assigned
A34: 35 | B34: 1281 | C34: US Accounts | D34: Bhartiya Darshika Naresh | E34: 40 | F34: Assigned
A35: 36 | B35: 1383 | C35: US Accounts | D35: Bhatt Nishant | E35: 40 | F35: Assigned
A36: 37 | B36: 1301 | C36: US Accounts | D36: Bihola Manavsinh Pravinsinh | E36: 40 | F36: Unassigned -FT
A37: 38 | B37: 1209 | C37: US Accounts | D37: Borkhetaria Jinit Jayesh | E37: 40 | F37: Assigned
A38: 39 | B38: 1201 | C38: US Accounts | D38: Chauhan Bhagirathsinh | E38: 40 | F38: Assigned
A39: 40 | B39: 1237 | C39: US Accounts | D39: Chawla Aman | E39: 40 | F39: Assigned
A40: 41 | B40: 1247 | C40: US Accounts | D40: Chhatrodiya Akshaykumar Hirabhai | E40: 40 | F40: Assigned
... A164: 165 | B164: 1388 | C164: US Tax | D164: Saurabh Dabi | E164: 40 | F164: Unassigned

Sheet Summary report
A1: Department Name | B1: T1 | C1: Employee ID | D1: Employee Name | E1: Assigned/Unassigned | F1: Billable Hours | G1: Non-Billable Hours | H1: Leave Hours | I1: Total Hours | J1: Expected Hours | K1: Effective Hours | L1: Billable Efficiency % | M1: Non-Billable Efficiency % | N1: Total Efficiency % | O1: Missing Hours
A2: Administration | B2: 1275 - Devendra Singh - Rana | C2: 1312 | D2: Kamda Brijeshkumar Rai | E2: =IFERROR(VLOOKUP(C2,'Expected hours per employee'!B:F,5,FALSE),"") | F2: =SUMIFS('Raw Data'!M:M,'Raw Data'!E:E,C2) | G2: =SUMIFS('Raw Data'!N:N,'Raw Data'!E:E,C2) | H2: =SUMIFS('Raw Data'!P:P,'Raw Data'!E:E,C2) | I2: =F2+G2+H2 | J2: =IFERROR(VLOOKUP(C2,'Expected hours per employee'!B:E,4,FALSE),0) | K2: =J2-H2 | L2: =IFERROR(F2/K2,0) | M2: =IFERROR(G2/K2,0) | N2: =L2+M2 | O2: =J2-I2
A3: Administration | B3: 1279 - Vimal - Vadhiya | C3: 1275 | D3: Devendra Singh Nandan Singh Rana | E3: =IFERROR(VLOOKUP(C3,'Expected hours per employee'!B:F,5,FALSE),"") | F3: =SUMIFS('Raw Data'!M:M,'Raw Data'!E:E,C3) | G3: =SUMIFS('Raw Data'!N:N,'Raw Data'!E:E,C3) | H3: =SUMIFS('Raw Data'!P:P,'Raw Data'!E:E,C3) | I3: =F3+G3+H3 | J3: =IFERROR(VLOOKUP(C3,'Expected hours per employee'!B:E,4,FALSE),0) | K3: =J3-H3 | L3: =IFERROR(F3/K3,0) | M3: =IFERROR(G3/K3,0) | N3: =L3+M3 | O3: =J3-I3
A4: Administration | B4: 1279 - Vimal - Vadhiya | C4: 1385 | D4: Vaishnavi | E4: =IFERROR(VLOOKUP(C4,'Expected hours per employee'!B:F,5,FALSE),"") | F4: =SUMIFS('Raw Data'!M:M,'Raw Data'!E:E,C4) | G4: =SUMIFS('Raw Data'!N:N,'Raw Data'!E:E,C4) | H4: =SUMIFS('Raw Data'!P:P,'Raw Data'!E:E,C4) | I4: =F4+G4+H4 | J4: =IFERROR(VLOOKUP(C4,'Expected hours per employee'!B:E,4,FALSE),0) | K4: =J4-H4 | L4: =IFERROR(F4/K4,0) | M4: =IFERROR(G4/K4,0) | N4: =L4+M4 | O4: =J4-I4
A5: Business Development | B5: 1279 - Vimal - Vadhiya | C5: 1276 | D5: Thakkar Dhara Chandrakantbhai | E5: =IFERROR(VLOOKUP(C5,'Expected hours per employee'!B:F,5,FALSE),"") | F5: =SUMIFS('Raw Data'!M:M,'Raw Data'!E:E,C5) | G5: =SUMIFS('Raw Data'!N:N,'Raw Data'!E:E,C5) | H5: =SUMIFS('Raw Data'!P:P,'Raw Data'!E:E,C5) | I5: =F5+G5+H5 | J5: =IFERROR(VLOOKUP(C5,'Expected hours per employee'!B:E,4,FALSE),0) | K5: =J5-H5 | L5: =IFERROR(F5/K5,0) | M5: =IFERROR(G5/K5,0) | N5: =L5+M5 | O5: =J5-I5
A6: Business Development | B6: 1279 - Vimal - Vadhiya | C6: 1118 | D6: Thakkarar Surav Rajesh | E6: =IFERROR(VLOOKUP(C6,'Expected hours per employee'!B:F,5,FALSE),"") | F6: =SUMIFS('Raw Data'!M:M,'Raw Data'!E:E,C6) | G6: =SUMIFS('Raw Data'!N:N,'Raw Data'!E:E,C6) | H6: =SUMIFS('Raw Data'!P:P,'Raw Data'!E:E,C6) | I6: =F6+G6+H6 | J6: =IFERROR(VLOOKUP(C6,'Expected hours per employee'!B:E,4,FALSE),0) | K6: =J6-H6 | L6: =IFERROR(F6/K6,0) | M6: =IFERROR(G6/K6,0) | N6: =L6+M6 | O6: =J6-I6
A7: Finance | B7: 1001 - Vivek - Shah | C7: 1249 | D7: Kapil Kanaiyalal Popat | E7: =IFERROR(VLOOKUP(C7,'Expected hours per employee'!B:F,5,FALSE),"") | F7: =SUMIFS('Raw Data'!M:M,'Raw Data'!E:E,C7) | G7: =SUMIFS('Raw Data'!N:N,'Raw Data'!E:E,C7) | H7: =SUMIFS('Raw Data'!P:P,'Raw Data'!E:E,C7) | I7: =F7+G7+H7 | J7: =IFERROR(VLOOKUP(C7,'Expected hours per employee'!B:E,4,FALSE),0) | K7: =J7-H7 | L7: =IFERROR(F7/K7,0) | M7: =IFERROR(G7/K7,0) | N7: =L7+M7 | O7: =J7-I7
A8: Finance | B8: 1249 - Kapil - Popat | C8: 229 | D8: Krunal K Panchal | E8: =IFERROR(VLOOKUP(C8,'Expected hours per employee'!B:F,5,FALSE),"") | F8: =SUMIFS('Raw Data'!M:M,'Raw Data'!E:E,C8) | G8: =SUMIFS('Raw Data'!N:N,'Raw Data'!E:E,C8) | H8: =SUMIFS('Raw Data'!P:P,'Raw Data'!E:E,C8) | I8: =F8+G8+H8 | J8: =IFERROR(VLOOKUP(C8,'Expected hours per employee'!B:E,4,FALSE),0) | K8: =J8-H8 | L8: =IFERROR(F8/K8,0) | M8: =IFERROR(G8/K8,0) | N8: =L8+M8 | O8: =J8-I8
A9: Finance | B9: 1279 - Vimal - Vadhiya | C9: 1371 | D9: Doshi Ankit Yogeshchandra | E9: =IFERROR(VLOOKUP(C9,'Expected hours per employee'!B:F,5,FALSE),"") | F9: =SUMIFS('Raw Data'!M:M,'Raw Data'!E:E,C9) | G9: =SUMIFS('Raw Data'!N:N,'Raw Data'!E:E,C9) | H9: =SUMIFS('Raw Data'!P:P,'Raw Data'!E:E,C9) | I9: =F9+G9+H9 | J9: =IFERROR(VLOOKUP(C9,'Expected hours per employee'!B:E,4,FALSE),0) | K9: =J9-H9 | L9: =IFERROR(F9/K9,0) | M9: =IFERROR(G9/K9,0) | N9: =L9+M9 | O9: =J9-I9
A10: HR | B10: 1249 - Kapil - Popat | C10: 1366 | D10: Digvijaysinh Indrajitsinh Rathod | E10: =IFERROR(VLOOKUP(C10,'Expected hours per employee'!B:F,5,FALSE),"") | F10: =SUMIFS('Raw Data'!M:M,'Raw Data'!E:E,C10) | G10: =SUMIFS('Raw Data'!N:N,'Raw Data'!E:E,C10) | H10: =SUMIFS('Raw Data'!P:P,'Raw Data'!E:E,C10) | I10: =F10+G10+H10 | J10: =IFERROR(VLOOKUP(C10,'Expected hours per employee'!B:E,4,FALSE),0) | K10: =J10-H10 | L10: =IFERROR(F10/K10,0) | M10: =IFERROR(G10/K10,0) | N10: =L10+M10 | O10: =J10-I10
A11: HR | B11: 1366 - Digvijaysinh - Rathod | C11: 1379 | D11: Bhadiyadra Bansari Ashokkumar | E11: =IFERROR(VLOOKUP(C11,'Expected hours per employee'!B:F,5,FALSE),"") | F11: =SUMIFS('Raw Data'!M:M,'Raw Data'!E:E,C11) | G11: =SUMIFS('Raw Data'!N:N,'Raw Data'!E:E,C11) | H11: =SUMIFS('Raw Data'!P:P,'Raw Data'!E:E,C11) | I11: =F11+G11+H11 | J11: =IFERROR(VLOOKUP(C11,'Expected hours per employee'!B:E,4,FALSE),0) | K11: =J11-H11 | L11: =IFERROR(F11/K11,0) | M11: =IFERROR(G11/K11,0) | N11: =L11+M11 | O11: =J11-I11
A12: HR | B12: 1366 - Digvijaysinh - Rathod | C12: 1234 | D12: Kavya Punitbhai Trivedi | E12: =IFERROR(VLOOKUP(C12,'Expected hours per employee'!B:F,5,FALSE),"") | F12: =SUMIFS('Raw Data'!M:M,'Raw Data'!E:E,C12) | G12: =SUMIFS('Raw Data'!N:N,'Raw Data'!E:E,C12) | H12: =SUMIFS('Raw Data'!P:P,'Raw Data'!E:E,C12) | I12: =F12+G12+H12 | J12: =IFERROR(VLOOKUP(C12,'Expected hours per employee'!B:E,4,FALSE),0) | K12: =J12-H12 | L12: =IFERROR(F12/K12,0) | M12: =IFERROR(G12/K12,0) | N12: =L12+M12 | O12: =J12-I12
A13: HR | B13: 1366 - Digvijaysinh - Rathod | C13: 1245 | D13: Khattri Aakash Premkumar | E13: =IFERROR(VLOOKUP(C13,'Expected hours per employee'!B:F,5,FALSE),"") | F13: =SUMIFS('Raw Data'!M:M,'Raw Data'!E:E,C13) | G13: =SUMIFS('Raw Data'!N:N,'Raw Data'!E:E,C13) | H13: =SUMIFS('Raw Data'!P:P,'Raw Data'!E:E,C13) | I13: =F13+G13+H13 | J13: =IFERROR(VLOOKUP(C13,'Expected hours per employee'!B:E,4,FALSE),0) | K13: =J13-H13 | L13: =IFERROR(F13/K13,0) | M13: =IFERROR(G13/K13,0) | N13: =L13+M13 | O13: =J13-I13
... A153: US Tax | B153: 224 - Ritesh - Sanghvi | C153: 1377 | D153: Vishal Bipinbhai Savadia | E153: =IFERROR(VLOOKUP(C153,'Expected hours per employee'!B:F,5,FALSE),"") | F153: =SUMIFS('Raw Data'!M:M,'Raw Data'!E:E,C153) | G153: =SUMIFS('Raw Data'!N:N,'Raw Data'!E:E,C153) | H153: =SUMIFS('Raw Data'!P:P,'Raw Data'!E:E,C153) | I153: =F153+G153+H153 | J153: =IFERROR(VLOOKUP(C153,'Expected hours per employee'!B:E,4,FALSE),0) | K153: =J153-H153 | L153: =IFERROR(F153/K153,0) | M153: =IFERROR(G153/K153,0) | N153: =L153+M153 | O153: =J153-I153
